nitric/__init__.py
nitric/application.py
nitric/bidi.py
nitric/channel.py
nitric/context.py
nitric/exception.py
nitric/py.typed
nitric/utils.py
nitric/config/__init__.py
nitric/proto/__init__.py
nitric/proto/KeyValue/__init__.py
nitric/proto/KeyValue/v1/__init__.py
nitric/proto/apis/__init__.py
nitric/proto/apis/v1/__init__.py
nitric/proto/batch/__init__.py
nitric/proto/batch/v1/__init__.py
nitric/proto/deployments/__init__.py
nitric/proto/deployments/v1/__init__.py
nitric/proto/http/__init__.py
nitric/proto/http/v1/__init__.py
nitric/proto/kvstore/__init__.py
nitric/proto/kvstore/v1/__init__.py
nitric/proto/queues/__init__.py
nitric/proto/queues/v1/__init__.py
nitric/proto/resources/__init__.py
nitric/proto/resources/v1/__init__.py
nitric/proto/schedules/__init__.py
nitric/proto/schedules/v1/__init__.py
nitric/proto/secrets/__init__.py
nitric/proto/secrets/v1/__init__.py
nitric/proto/sql/__init__.py
nitric/proto/sql/v1/__init__.py
nitric/proto/storage/__init__.py
nitric/proto/storage/v1/__init__.py
nitric/proto/topics/__init__.py
nitric/proto/topics/v1/__init__.py
nitric/proto/websockets/__init__.py
nitric/proto/websockets/v1/__init__.py
nitric/resources/__init__.py
nitric/resources/apis.py
nitric/resources/buckets.py
nitric/resources/job.py
nitric/resources/kv.py
nitric/resources/queues.py
nitric/resources/resource.py
nitric/resources/schedules.py
nitric/resources/secrets.py
nitric/resources/sql.py
nitric/resources/topics.py
nitric/resources/websockets.py
nitric-1.2.4.dist-info/METADATA
nitric-1.2.4.dist-info/WHEEL
nitric-1.2.4.dist-info/top_level.txt
nitric-1.2.4.dist-info/RECORD
