Metadata-Version: 2.1
Name: nitric
Version: 1.2.4
Summary: The Nitric SDK for Python 3
Home-page: https://github.com/nitrictech/python-sdk
Author: Nitric
Author-email: team@nitric.io
Classifier: Programming Language :: Python :: 3
Classifier: Operating System :: OS Independent
Requires-Python: >=3.11
Requires-Dist: asyncio
Requires-Dist: protobuf==4.23.3
Requires-Dist: betterproto==2.0.0b6
Requires-Dist: opentelemetry-api
Requires-Dist: opentelemetry-sdk
Requires-Dist: opentelemetry-exporter-otlp-proto-grpc
Requires-Dist: opentelemetry-instrumentation-grpc
Provides-Extra: dev
Requires-Dist: tox==3.20.1; extra == "dev"
Requires-Dist: twine==3.2.0; extra == "dev"
Requires-Dist: pytest==7.3.2; extra == "dev"
Requires-Dist: pytest-cov==4.1.0; extra == "dev"
Requires-Dist: pre-commit==2.12.0; extra == "dev"
Requires-Dist: black==22.3; extra == "dev"
Requires-Dist: flake8==3.9.1; extra == "dev"
Requires-Dist: flake8; extra == "dev"
Requires-Dist: flake8-bugbear; extra == "dev"
Requires-Dist: flake8-comprehensions; extra == "dev"
Requires-Dist: flake8-string-format; extra == "dev"
Requires-Dist: pydocstyle==6.0.0; extra == "dev"
Requires-Dist: pip-licenses==3.3.1; extra == "dev"
Requires-Dist: licenseheaders==0.8.8; extra == "dev"
Requires-Dist: pdoc3==0.9.2; extra == "dev"
Requires-Dist: markupsafe==2.0.1; extra == "dev"
Requires-Dist: betterproto[compiler]==2.0.0b6; extra == "dev"
Requires-Dist: grpcio-tools==1.62.0; extra == "dev"
Requires-Dist: mypy==1.3.0; extra == "dev"
